extend_orfs/__init__.py
extend_orfs/the_script_extend_orfs.py
extend_orfs-0.0.1111111.dist-info/METADATA
extend_orfs-0.0.1111111.dist-info/WHEEL
extend_orfs-0.0.1111111.dist-info/top_level.txt
extend_orfs-0.0.1111111.dist-info/RECORD
