Metadata-Version: 2.1
Name: extend-orfs
Version: 0.0.1111111
Summary: MModule description
Home-page: https://github.com/JoanPAAL/extend_orfs/
Author: Joan Pallarès-Albanell
Author-email: joan.pallares.albanell@gmail.com
Classifier: Programming Language :: Python :: 3
Classifier: License :: OSI Approved :: MIT License
Classifier: Operating System :: OS Independent
Requires-Python: >=3.7.13
Requires-Dist: pyranges (>=0.0.117)
Requires-Dist: pyfaidx (>=0.7.1)
Requires-Dist: pandas (>=1.3.5)
Requires-Dist: easyterm
